latent_explorer/__init__.py
latent_explorer/explorer.py
latent_explorer/kg.py
latent_explorer/llm.py
latent_explorer/patcher.py
latent_explorer/resources/in_context_examples.json
latent_explorer/utils/__init__.py
latent_explorer/utils/data_loader.py
latent_explorer/utils/graph.py
latent_explorer/utils/io.py
latent_explorer/utils/triples.py
latent_explorer/utils/utils.py
latent_explorer/utils/litgpt_minimal/__init__.py
latent_explorer/utils/litgpt_minimal/base.py
latent_explorer/utils/litgpt_minimal/model.py
latent_explorer/utils/litgpt_minimal/tokenizer.py
latent_explorer-0.1.5.dist-info/LICENSE
latent_explorer-0.1.5.dist-info/METADATA
latent_explorer-0.1.5.dist-info/WHEEL
latent_explorer-0.1.5.dist-info/top_level.txt
latent_explorer-0.1.5.dist-info/RECORD
