Metadata-Version: 2.1
Name: latent-explorer
Version: 0.1.5
Summary: A Python library based on the technique of activation patching to represent the factual knowledge encoded in the latent space of large language models as dynamic knowledge graphs.
Author: Ipazia AI
Maintainer-email: Marco Bronzini <m.bronzini@ipazia.com>
License: CC BY-NC-SA 4.0
Project-URL: Repository, https://github.com/Ipazia-AI/latent-explorer
Project-URL: Homepage, https://github.com/Ipazia-AI
Keywords: Large Language Models,Latent Representations,Graphs,Factual Knowledge,Activation Patching,Probes,Residual Stream
Classifier: Programming Language :: Python :: 3
Classifier: Operating System :: OS Independent
Classifier: License :: Free for non-commercial use
Classifier: Development Status :: 3 - Alpha
Classifier: Intended Audience :: Developers
Classifier: Intended Audience :: Education
Classifier: Intended Audience :: Science/Research
Classifier: Topic :: Scientific/Engineering :: Artificial Intelligence
Requires-Python: >=3.9
License-File: LICENSE
Requires-Dist: litgpt
Requires-Dist: huggingface-hub
Requires-Dist: tokenizers
Requires-Dist: spacy
Requires-Dist: spacy-curated-transformers
Requires-Dist: pandas
Requires-Dist: safetensors
Requires-Dist: dirtyjson
Requires-Dist: matplotlib
Requires-Dist: networkx-temporal
